vscode_copilot_controller/__init__.py
vscode_copilot_controller/__main__.py
vscode_copilot_controller/_version.py
vscode_copilot_controller/cli.py
vscode_copilot_controller/config.py
vscode_copilot_controller/engine.py
vscode_copilot_controller/exceptions.py
vscode_copilot_controller/py.typed
vscode_copilot_controller/detectors/__init__.py
vscode_copilot_controller/detectors/base.py
vscode_copilot_controller/detectors/button_detector.py
vscode_copilot_controller/detectors/input_detector.py
vscode_copilot_controller/detectors/status_detector.py
vscode_copilot_controller/utils/__init__.py
vscode_copilot_controller/utils/area_config.py
vscode_copilot_controller/utils/mouse_tracker.py
vscode_copilot_controller/utils/screen_selector.py
vscode_copilot_controller-0.1.8.dist-info/licenses/LICENSE
vscode_copilot_controller-0.1.8.dist-info/METADATA
vscode_copilot_controller-0.1.8.dist-info/WHEEL
vscode_copilot_controller-0.1.8.dist-info/entry_points.txt
vscode_copilot_controller-0.1.8.dist-info/top_level.txt
vscode_copilot_controller-0.1.8.dist-info/RECORD
