Metadata-Version: 2.4
Name: vscode-copilot-controller
Version: 0.1.8
Summary: Programmatically control VSCode Copilot chat panel using OCR-based UI automation
Author-email: AutoOcto Team <team@autoocto.dev>
License-Expression: MIT
Project-URL: Homepage, https://github.com/autoocto/vscode-copilot-controller
Project-URL: Bug Tracker, https://github.com/autoocto/vscode-copilot-controller/issues
Project-URL: Documentation, https://github.com/autoocto/vscode-copilot-controller/wiki
Project-URL: Source Code, https://github.com/autoocto/vscode-copilot-controller
Keywords: vscode,copilot,automation,ocr,ui-testing,chat-control,tesseract,image-recognition
Classifier: Development Status :: 4 - Beta
Classifier: Intended Audience :: Developers
Classifier: Topic :: Software Development :: Testing
Classifier: Topic :: Software Development :: User Interfaces
Classifier: Programming Language :: Python :: 3
Classifier: Programming Language :: Python :: 3.8
Classifier: Programming Language :: Python :: 3.9
Classifier: Programming Language :: Python :: 3.10
Classifier: Programming Language :: Python :: 3.11
Classifier: Programming Language :: Python :: 3.12
Classifier: Operating System :: OS Independent
Classifier: Topic :: Scientific/Engineering :: Image Recognition
Requires-Python: >=3.8
License-File: LICENSE
Requires-Dist: pillow>=8.0.0
Requires-Dist: pytesseract>=0.3.8
Requires-Dist: pyautogui>=0.9.53
Provides-Extra: dev
Requires-Dist: pytest>=6.0; extra == "dev"
Requires-Dist: pytest-cov>=2.10; extra == "dev"
Requires-Dist: black>=21.0; extra == "dev"
Requires-Dist: isort>=5.0; extra == "dev"
Requires-Dist: flake8>=3.8; extra == "dev"
Requires-Dist: mypy>=0.900; extra == "dev"
Provides-Extra: docs
Requires-Dist: sphinx>=4.0; extra == "docs"
Requires-Dist: sphinx-rtd-theme>=1.0; extra == "docs"
Provides-Extra: gui
Requires-Dist: pygetwindow>=0.0.9; extra == "gui"
Requires-Dist: tkinter; platform_system != "Darwin" and extra == "gui"
Dynamic: license-file
